hrepr/__init__.py
hrepr/core.py
hrepr/elements.py
hrepr/h.py
hrepr/hgen.py
hrepr/hlib.js
hrepr/j.py
hrepr/make.py
hrepr/resource.py
hrepr/textgen.py
hrepr/version.py
hrepr/style/hrepr.css
hrepr/style/nbreset.css
hrepr-0.9.1.dist-info/METADATA
hrepr-0.9.1.dist-info/WHEEL
hrepr-0.9.1.dist-info/licenses/LICENSE
hrepr-0.9.1.dist-info/RECORD
