Metadata-Version: 2.4
Name: hrepr
Version: 0.9.1
Summary: Extensible HTML representation for Python objects.
Project-URL: Homepage, https://github.com/breuleux/hrepr
Project-URL: Repository, https://github.com/breuleux/hrepr
Author-email: Olivier Breuleux <breuleux@gmail.com>
License-Expression: MIT
License-File: LICENSE
Classifier: Development Status :: 4 - Beta
Classifier: Intended Audience :: Developers
Requires-Python: >=3.9
Requires-Dist: ovld~=0.5.1
